bSuite/auth/__init__.py
bSuite/auth/client.py
bSuite/auth/etc.py
bSuite/auth/middleware.py
bSuite_auth-0.5.1.dist-info/LICENSE
bSuite_auth-0.5.1.dist-info/METADATA
bSuite_auth-0.5.1.dist-info/WHEEL
bSuite_auth-0.5.1.dist-info/top_level.txt
bSuite_auth-0.5.1.dist-info/RECORD
