Metadata-Version: 2.1
Name: bSuite-auth
Version: 0.5.1
Summary: authentication submodule of bSuite
Author-email: John Birdwell <j.c.birdwell@gmail.com>
License: GNU GENERAL PUBLIC LICENSE
Requires-Python: >=3.11
License-File: LICENSE
Requires-Dist: fastapi
Requires-Dist: requests
Requires-Dist: starlette
Requires-Dist: cryptography
